{
  "id": "0637c467-60ae-455e-9676-f1453ef81acd",
  "prevId": "52325d64-d646-4b0c-8fe8-6a2741fbc8a6",
  "version": "5",
  "dialect": "mysql",
  "tables": {
    "email_logs": {
      "name": "email_logs",
      "columns": {
        "id": {
          "name": "id",
          "type": "varchar(36)",
          "primaryKey": false,
          "notNull": true,
          "autoincrement": false
        },
        "application_id": {
          "name": "application_id",
          "type": "varchar(36)",
          "primaryKey": false,
          "notNull": true,
          "autoincrement": false
        },
        "application_type": {
          "name": "application_type",
          "type": "varchar(20)",
          "primaryKey": false,
          "notNull": true,
          "autoincrement": false
        },
        "email_type": {
          "name": "email_type",
          "type": "varchar(20)",
          "primaryKey": false,
          "notNull": true,
          "autoincrement": false
        },
        "recipient_email": {
          "name": "recipient_email",
          "type": "text",
          "primaryKey": false,
          "notNull": true,
          "autoincrement": false
        },
        "status": {
          "name": "status",
          "type": "varchar(20)",
          "primaryKey": false,
          "notNull": true,
          "autoincrement": false,
          "default": "'SENT'"
        },
        "sent_at": {
          "name": "sent_at",
          "type": "timestamp",
          "primaryKey": false,
          "notNull": true,
          "autoincrement": false,
          "default": "(now())"
        }
      },
      "indexes": {
        "email_logs_application_idx": {
          "name": "email_logs_application_idx",
          "columns": [
            "application_id"
          ],
          "isUnique": false
        },
        "email_logs_type_idx": {
          "name": "email_logs_type_idx",
          "columns": [
            "application_type",
            "email_type"
          ],
          "isUnique": false
        },
        "email_logs_sent_at_idx": {
          "name": "email_logs_sent_at_idx",
          "columns": [
            "sent_at"
          ],
          "isUnique": false
        }
      },
      "foreignKeys": {},
      "compositePrimaryKeys": {
        "email_logs_id": {
          "name": "email_logs_id",
          "columns": [
            "id"
          ]
        }
      },
      "uniqueConstraints": {},
      "checkConstraint": {}
    },
    "email_presets": {
      "name": "email_presets",
      "columns": {
        "id": {
          "name": "id",
          "type": "varchar(36)",
          "primaryKey": false,
          "notNull": true,
          "autoincrement": false
        },
        "key": {
          "name": "key",
          "type": "varchar(64)",
          "primaryKey": false,
          "notNull": true,
          "autoincrement": false
        },
        "application_type": {
          "name": "application_type",
          "type": "varchar(20)",
          "primaryKey": false,
          "notNull": true,
          "autoincrement": false
        },
        "category": {
          "name": "category",
          "type": "varchar(20)",
          "primaryKey": false,
          "notNull": true,
          "autoincrement": false
        },
        "status": {
          "name": "status",
          "type": "varchar(20)",
          "primaryKey": false,
          "notNull": false,
          "autoincrement": false
        },
        "subject_template": {
          "name": "subject_template",
          "type": "text",
          "primaryKey": false,
          "notNull": true,
          "autoincrement": false
        },
        "html_template": {
          "name": "html_template",
          "type": "text",
          "primaryKey": false,
          "notNull": true,
          "autoincrement": false
        },
        "default_tokens": {
          "name": "default_tokens",
          "type": "text",
          "primaryKey": false,
          "notNull": false,
          "autoincrement": false
        },
        "created_at": {
          "name": "created_at",
          "type": "timestamp",
          "primaryKey": false,
          "notNull": true,
          "autoincrement": false,
          "default": "(now())"
        },
        "updated_at": {
          "name": "updated_at",
          "type": "timestamp",
          "primaryKey": false,
          "notNull": true,
          "autoincrement": false,
          "default": "(now())"
        }
      },
      "indexes": {
        "email_presets_key_idx": {
          "name": "email_presets_key_idx",
          "columns": [
            "key"
          ],
          "isUnique": false
        },
        "email_presets_type_idx": {
          "name": "email_presets_type_idx",
          "columns": [
            "application_type"
          ],
          "isUnique": false
        },
        "email_presets_status_idx": {
          "name": "email_presets_status_idx",
          "columns": [
            "status"
          ],
          "isUnique": false
        },
        "uniq_preset_key_type_status": {
          "name": "uniq_preset_key_type_status",
          "columns": [
            "key",
            "application_type",
            "status"
          ],
          "isUnique": true
        }
      },
      "foreignKeys": {},
      "compositePrimaryKeys": {
        "email_presets_id": {
          "name": "email_presets_id",
          "columns": [
            "id"
          ]
        }
      },
      "uniqueConstraints": {},
      "checkConstraint": {}
    },
    "event_rsvp_answers": {
      "name": "event_rsvp_answers",
      "columns": {
        "id": {
          "name": "id",
          "type": "varchar(36)",
          "primaryKey": false,
          "notNull": true,
          "autoincrement": false
        },
        "event_id": {
          "name": "event_id",
          "type": "varchar(64)",
          "primaryKey": false,
          "notNull": true,
          "autoincrement": false
        },
        "user_id": {
          "name": "user_id",
          "type": "varchar(36)",
          "primaryKey": false,
          "notNull": true,
          "autoincrement": false
        },
        "question_key": {
          "name": "question_key",
          "type": "varchar(64)",
          "primaryKey": false,
          "notNull": true,
          "autoincrement": false
        },
        "answer": {
          "name": "answer",
          "type": "text",
          "primaryKey": false,
          "notNull": true,
          "autoincrement": false
        },
        "created_at": {
          "name": "created_at",
          "type": "timestamp",
          "primaryKey": false,
          "notNull": true,
          "autoincrement": false,
          "default": "(now())"
        },
        "updated_at": {
          "name": "updated_at",
          "type": "timestamp",
          "primaryKey": false,
          "notNull": true,
          "autoincrement": false,
          "default": "(now())"
        }
      },
      "indexes": {
        "event_rsvp_answers_event_idx": {
          "name": "event_rsvp_answers_event_idx",
          "columns": [
            "event_id"
          ],
          "isUnique": false
        },
        "event_rsvp_answers_user_idx": {
          "name": "event_rsvp_answers_user_idx",
          "columns": [
            "user_id"
          ],
          "isUnique": false
        },
        "event_rsvp_answers_question_idx": {
          "name": "event_rsvp_answers_question_idx",
          "columns": [
            "question_key"
          ],
          "isUnique": false
        },
        "uniq_event_user_question": {
          "name": "uniq_event_user_question",
          "columns": [
            "event_id",
            "user_id",
            "question_key"
          ],
          "isUnique": true
        }
      },
      "foreignKeys": {},
      "compositePrimaryKeys": {
        "event_rsvp_answers_id": {
          "name": "event_rsvp_answers_id",
          "columns": [
            "id"
          ]
        }
      },
      "uniqueConstraints": {},
      "checkConstraint": {}
    },
    "event_rsvps": {
      "name": "event_rsvps",
      "columns": {
        "id": {
          "name": "id",
          "type": "varchar(36)",
          "primaryKey": false,
          "notNull": true,
          "autoincrement": false
        },
        "event_id": {
          "name": "event_id",
          "type": "varchar(64)",
          "primaryKey": false,
          "notNull": true,
          "autoincrement": false
        },
        "user_id": {
          "name": "user_id",
          "type": "varchar(36)",
          "primaryKey": false,
          "notNull": true,
          "autoincrement": false
        },
        "created_at": {
          "name": "created_at",
          "type": "timestamp",
          "primaryKey": false,
          "notNull": true,
          "autoincrement": false,
          "default": "(now())"
        }
      },
      "indexes": {
        "event_rsvps_event_idx": {
          "name": "event_rsvps_event_idx",
          "columns": [
            "event_id"
          ],
          "isUnique": false
        },
        "event_rsvps_user_idx": {
          "name": "event_rsvps_user_idx",
          "columns": [
            "user_id"
          ],
          "isUnique": false
        },
        "uniq_event_user": {
          "name": "uniq_event_user",
          "columns": [
            "event_id",
            "user_id"
          ],
          "isUnique": true
        }
      },
      "foreignKeys": {},
      "compositePrimaryKeys": {
        "event_rsvps_id": {
          "name": "event_rsvps_id",
          "columns": [
            "id"
          ]
        }
      },
      "uniqueConstraints": {},
      "checkConstraint": {}
    },
    "fund_applications": {
      "name": "fund_applications",
      "columns": {
        "id": {
          "name": "id",
          "type": "varchar(36)",
          "primaryKey": false,
          "notNull": true,
          "autoincrement": false
        },
        "user_id": {
          "name": "user_id",
          "type": "varchar(36)",
          "primaryKey": false,
          "notNull": true,
          "autoincrement": false
        },
        "name": {
          "name": "name",
          "type": "text",
          "primaryKey": false,
          "notNull": true,
          "autoincrement": false
        },
        "email": {
          "name": "email",
          "type": "text",
          "primaryKey": false,
          "notNull": true,
          "autoincrement": false
        },
        "age": {
          "name": "age",
          "type": "int",
          "primaryKey": false,
          "notNull": true,
          "autoincrement": false
        },
        "zipcode": {
          "name": "zipcode",
          "type": "text",
          "primaryKey": false,
          "notNull": true,
          "autoincrement": false
        },
        "race": {
          "name": "race",
          "type": "varchar(255)",
          "primaryKey": false,
          "notNull": true,
          "autoincrement": false
        },
        "race_date": {
          "name": "race_date",
          "type": "timestamp",
          "primaryKey": false,
          "notNull": false,
          "autoincrement": false
        },
        "race_location": {
          "name": "race_location",
          "type": "text",
          "primaryKey": false,
          "notNull": false,
          "autoincrement": false
        },
        "first_race": {
          "name": "first_race",
          "type": "boolean",
          "primaryKey": false,
          "notNull": true,
          "autoincrement": false
        },
        "experience": {
          "name": "experience",
          "type": "text",
          "primaryKey": false,
          "notNull": true,
          "autoincrement": false
        },
        "reason": {
          "name": "reason",
          "type": "text",
          "primaryKey": false,
          "notNull": true,
          "autoincrement": false
        },
        "goals": {
          "name": "goals",
          "type": "text",
          "primaryKey": false,
          "notNull": false,
          "autoincrement": false
        },
        "involvement": {
          "name": "involvement",
          "type": "text",
          "primaryKey": false,
          "notNull": true,
          "autoincrement": false
        },
        "bipoc_identity": {
          "name": "bipoc_identity",
          "type": "boolean",
          "primaryKey": false,
          "notNull": true,
          "autoincrement": false
        },
        "gender_identity": {
          "name": "gender_identity",
          "type": "text",
          "primaryKey": false,
          "notNull": true,
          "autoincrement": false
        },
        "additional_assistance_needs": {
          "name": "additional_assistance_needs",
          "type": "text",
          "primaryKey": false,
          "notNull": false,
          "autoincrement": false
        },
        "referral_source": {
          "name": "referral_source",
          "type": "text",
          "primaryKey": false,
          "notNull": true,
          "autoincrement": false
        },
        "gear_needs": {
          "name": "gear_needs",
          "type": "text",
          "primaryKey": false,
          "notNull": false,
          "autoincrement": false
        },
        "wants_mentor": {
          "name": "wants_mentor",
          "type": "boolean",
          "primaryKey": false,
          "notNull": true,
          "autoincrement": false,
          "default": false
        },
        "mentor_gender_preference": {
          "name": "mentor_gender_preference",
          "type": "text",
          "primaryKey": false,
          "notNull": false,
          "autoincrement": false
        },
        "status": {
          "name": "status",
          "type": "varchar(50)",
          "primaryKey": false,
          "notNull": true,
          "autoincrement": false,
          "default": "'PENDING'"
        },
        "registration_status": {
          "name": "registration_status",
          "type": "varchar(50)",
          "primaryKey": false,
          "notNull": true,
          "autoincrement": false,
          "default": "'PENDING'"
        },
        "admin_notes": {
          "name": "admin_notes",
          "type": "text",
          "primaryKey": false,
          "notNull": false,
          "autoincrement": false
        },
        "created_at": {
          "name": "created_at",
          "type": "timestamp",
          "primaryKey": false,
          "notNull": true,
          "autoincrement": false,
          "default": "(now())"
        },
        "updated_at": {
          "name": "updated_at",
          "type": "timestamp",
          "primaryKey": false,
          "notNull": true,
          "autoincrement": false,
          "default": "(now())"
        }
      },
      "indexes": {
        "fund_applications_created_at_idx": {
          "name": "fund_applications_created_at_idx",
          "columns": [
            "created_at"
          ],
          "isUnique": false
        },
        "fund_applications_status_idx": {
          "name": "fund_applications_status_idx",
          "columns": [
            "status"
          ],
          "isUnique": false
        },
        "fund_applications_user_created_at_idx": {
          "name": "fund_applications_user_created_at_idx",
          "columns": [
            "user_id",
            "created_at"
          ],
          "isUnique": false
        }
      },
      "foreignKeys": {},
      "compositePrimaryKeys": {
        "fund_applications_id": {
          "name": "fund_applications_id",
          "columns": [
            "id"
          ]
        }
      },
      "uniqueConstraints": {},
      "checkConstraint": {}
    },
    "mentor_applications": {
      "name": "mentor_applications",
      "columns": {
        "id": {
          "name": "id",
          "type": "varchar(36)",
          "primaryKey": false,
          "notNull": true,
          "autoincrement": false
        },
        "user_id": {
          "name": "user_id",
          "type": "varchar(36)",
          "primaryKey": false,
          "notNull": true,
          "autoincrement": false
        },
        "name": {
          "name": "name",
          "type": "text",
          "primaryKey": false,
          "notNull": true,
          "autoincrement": false
        },
        "email": {
          "name": "email",
          "type": "text",
          "primaryKey": false,
          "notNull": true,
          "autoincrement": false
        },
        "pronouns": {
          "name": "pronouns",
          "type": "text",
          "primaryKey": false,
          "notNull": false,
          "autoincrement": false
        },
        "running_experience_years": {
          "name": "running_experience_years",
          "type": "int",
          "primaryKey": false,
          "notNull": false,
          "autoincrement": false
        },
        "trail_running_experience_years": {
          "name": "trail_running_experience_years",
          "type": "int",
          "primaryKey": false,
          "notNull": false,
          "autoincrement": false
        },
        "mentorship_experience": {
          "name": "mentorship_experience",
          "type": "text",
          "primaryKey": false,
          "notNull": false,
          "autoincrement": false
        },
        "motivation_to_mentor": {
          "name": "motivation_to_mentor",
          "type": "text",
          "primaryKey": false,
          "notNull": true,
          "autoincrement": false
        },
        "preferred_communication_style": {
          "name": "preferred_communication_style",
          "type": "text",
          "primaryKey": false,
          "notNull": true,
          "autoincrement": false
        },
        "availability": {
          "name": "availability",
          "type": "text",
          "primaryKey": false,
          "notNull": true,
          "autoincrement": false
        },
        "special_expertise": {
          "name": "special_expertise",
          "type": "text",
          "primaryKey": false,
          "notNull": false,
          "autoincrement": false
        },
        "bipoc_identity": {
          "name": "bipoc_identity",
          "type": "boolean",
          "primaryKey": false,
          "notNull": false,
          "autoincrement": false
        },
        "gender_identity": {
          "name": "gender_identity",
          "type": "text",
          "primaryKey": false,
          "notNull": false,
          "autoincrement": false
        },
        "mentor_gender_preference": {
          "name": "mentor_gender_preference",
          "type": "text",
          "primaryKey": false,
          "notNull": false,
          "autoincrement": false
        },
        "location_region": {
          "name": "location_region",
          "type": "text",
          "primaryKey": false,
          "notNull": false,
          "autoincrement": false
        },
        "slack_username": {
          "name": "slack_username",
          "type": "text",
          "primaryKey": false,
          "notNull": false,
          "autoincrement": false
        },
        "additional_info": {
          "name": "additional_info",
          "type": "text",
          "primaryKey": false,
          "notNull": false,
          "autoincrement": false
        },
        "hear_about_program": {
          "name": "hear_about_program",
          "type": "text",
          "primaryKey": false,
          "notNull": true,
          "autoincrement": false
        },
        "status": {
          "name": "status",
          "type": "varchar(50)",
          "primaryKey": false,
          "notNull": true,
          "autoincrement": false,
          "default": "'PENDING'"
        },
        "created_at": {
          "name": "created_at",
          "type": "timestamp",
          "primaryKey": false,
          "notNull": true,
          "autoincrement": false,
          "default": "(now())"
        },
        "updated_at": {
          "name": "updated_at",
          "type": "timestamp",
          "primaryKey": false,
          "notNull": true,
          "autoincrement": false,
          "default": "(now())"
        }
      },
      "indexes": {
        "mentor_applications_created_at_idx": {
          "name": "mentor_applications_created_at_idx",
          "columns": [
            "created_at"
          ],
          "isUnique": false
        },
        "mentor_applications_status_idx": {
          "name": "mentor_applications_status_idx",
          "columns": [
            "status"
          ],
          "isUnique": false
        },
        "mentor_applications_user_created_at_idx": {
          "name": "mentor_applications_user_created_at_idx",
          "columns": [
            "user_id",
            "created_at"
          ],
          "isUnique": false
        }
      },
      "foreignKeys": {},
      "compositePrimaryKeys": {
        "mentor_applications_id": {
          "name": "mentor_applications_id",
          "columns": [
            "id"
          ]
        }
      },
      "uniqueConstraints": {},
      "checkConstraint": {}
    },
    "mentorship_matches": {
      "name": "mentorship_matches",
      "columns": {
        "id": {
          "name": "id",
          "type": "varchar(36)",
          "primaryKey": false,
          "notNull": true,
          "autoincrement": false
        },
        "fund_application_id": {
          "name": "fund_application_id",
          "type": "varchar(36)",
          "primaryKey": false,
          "notNull": true,
          "autoincrement": false
        },
        "mentor_application_id": {
          "name": "mentor_application_id",
          "type": "varchar(36)",
          "primaryKey": false,
          "notNull": true,
          "autoincrement": false
        },
        "admin_notes": {
          "name": "admin_notes",
          "type": "text",
          "primaryKey": false,
          "notNull": false,
          "autoincrement": false
        },
        "ended_at": {
          "name": "ended_at",
          "type": "timestamp",
          "primaryKey": false,
          "notNull": false,
          "autoincrement": false
        },
        "created_at": {
          "name": "created_at",
          "type": "timestamp",
          "primaryKey": false,
          "notNull": true,
          "autoincrement": false,
          "default": "(now())"
        },
        "updated_at": {
          "name": "updated_at",
          "type": "timestamp",
          "primaryKey": false,
          "notNull": true,
          "autoincrement": false,
          "default": "(now())"
        }
      },
      "indexes": {
        "mentorship_matches_created_at_idx": {
          "name": "mentorship_matches_created_at_idx",
          "columns": [
            "created_at"
          ],
          "isUnique": false
        },
        "mentorship_matches_fund_app_idx": {
          "name": "mentorship_matches_fund_app_idx",
          "columns": [
            "fund_application_id"
          ],
          "isUnique": false
        },
        "mentorship_matches_mentor_app_idx": {
          "name": "mentorship_matches_mentor_app_idx",
          "columns": [
            "mentor_application_id"
          ],
          "isUnique": false
        },
        "mentorship_matches_open_idx": {
          "name": "mentorship_matches_open_idx",
          "columns": [
            "fund_application_id",
            "ended_at"
          ],
          "isUnique": false
        }
      },
      "foreignKeys": {},
      "compositePrimaryKeys": {
        "mentorship_matches_id": {
          "name": "mentorship_matches_id",
          "columns": [
            "id"
          ]
        }
      },
      "uniqueConstraints": {},
      "checkConstraint": {}
    },
    "users": {
      "name": "users",
      "columns": {
        "id": {
          "name": "id",
          "type": "varchar(36)",
          "primaryKey": false,
          "notNull": true,
          "autoincrement": false
        },
        "clerk_id": {
          "name": "clerk_id",
          "type": "varchar(255)",
          "primaryKey": false,
          "notNull": true,
          "autoincrement": false
        },
        "email": {
          "name": "email",
          "type": "varchar(255)",
          "primaryKey": false,
          "notNull": true,
          "autoincrement": false
        },
        "name": {
          "name": "name",
          "type": "text",
          "primaryKey": false,
          "notNull": false,
          "autoincrement": false
        },
        "profile_image_url": {
          "name": "profile_image_url",
          "type": "text",
          "primaryKey": false,
          "notNull": false,
          "autoincrement": false
        },
        "user_type": {
          "name": "user_type",
          "type": "text",
          "primaryKey": false,
          "notNull": false,
          "autoincrement": false
        },
        "gender_identity": {
          "name": "gender_identity",
          "type": "text",
          "primaryKey": false,
          "notNull": false,
          "autoincrement": false
        },
        "pronouns": {
          "name": "pronouns",
          "type": "text",
          "primaryKey": false,
          "notNull": false,
          "autoincrement": false
        },
        "age": {
          "name": "age",
          "type": "int",
          "primaryKey": false,
          "notNull": false,
          "autoincrement": false
        },
        "location_region": {
          "name": "location_region",
          "type": "text",
          "primaryKey": false,
          "notNull": false,
          "autoincrement": false
        },
        "running_experience": {
          "name": "running_experience",
          "type": "text",
          "primaryKey": false,
          "notNull": false,
          "autoincrement": false
        },
        "hear_about": {
          "name": "hear_about",
          "type": "text",
          "primaryKey": false,
          "notNull": false,
          "autoincrement": false
        },
        "accepted_code_of_conduct": {
          "name": "accepted_code_of_conduct",
          "type": "boolean",
          "primaryKey": false,
          "notNull": true,
          "autoincrement": false,
          "default": false
        },
        "onboarding_completed": {
          "name": "onboarding_completed",
          "type": "boolean",
          "primaryKey": false,
          "notNull": true,
          "autoincrement": false,
          "default": false
        },
        "slack_joined": {
          "name": "slack_joined",
          "type": "boolean",
          "primaryKey": false,
          "notNull": true,
          "autoincrement": false,
          "default": false
        },
        "strava_joined": {
          "name": "strava_joined",
          "type": "boolean",
          "primaryKey": false,
          "notNull": true,
          "autoincrement": false,
          "default": false
        },
        "donation_completed": {
          "name": "donation_completed",
          "type": "boolean",
          "primaryKey": false,
          "notNull": true,
          "autoincrement": false,
          "default": false
        },
        "instagram_followed": {
          "name": "instagram_followed",
          "type": "boolean",
          "primaryKey": false,
          "notNull": true,
          "autoincrement": false,
          "default": false
        },
        "newsletter_subscribed": {
          "name": "newsletter_subscribed",
          "type": "boolean",
          "primaryKey": false,
          "notNull": true,
          "autoincrement": false,
          "default": false
        },
        "created_at": {
          "name": "created_at",
          "type": "timestamp",
          "primaryKey": false,
          "notNull": true,
          "autoincrement": false,
          "default": "(now())"
        },
        "updated_at": {
          "name": "updated_at",
          "type": "timestamp",
          "primaryKey": false,
          "notNull": true,
          "autoincrement": false,
          "default": "(now())"
        }
      },
      "indexes": {
        "users_created_at_idx": {
          "name": "users_created_at_idx",
          "columns": [
            "created_at"
          ],
          "isUnique": false
        },
        "users_email_idx": {
          "name": "users_email_idx",
          "columns": [
            "email"
          ],
          "isUnique": false
        }
      },
      "foreignKeys": {},
      "compositePrimaryKeys": {
        "users_id": {
          "name": "users_id",
          "columns": [
            "id"
          ]
        }
      },
      "uniqueConstraints": {},
      "checkConstraint": {}
    }
  },
  "views": {},
  "_meta": {
    "columns": {},
    "schemas": {},
    "tables": {}
  },
  "internal": {
    "tables": {},
    "indexes": {}
  }
}